LICENSE.GPL3
LICENSE.LGPL
MANIFEST.in
README.txt
setup.cfg
setup.py
PyUbootImage/PyUbootImage.py
PyUbootImage/__init__.py
PyUbootImage.egg-info/PKG-INFO
PyUbootImage.egg-info/SOURCES.txt
PyUbootImage.egg-info/dependency_links.txt
PyUbootImage.egg-info/top_level.txt
docs/Makefile
docs/conf.py
docs/getting_started.rst
docs/index.rst
docs/make.bat