Metadata-Version: 1.1
Name: PyUbootImage
Version: 0.3
Summary: Uboot image parser
Home-page: https://github.com/matteomattei/PyUbootImage
Author: Matteo Mattei; Nicola Ponzeveroni; Roberto Celeste
Author-email: info@matteomattei.com; nicola.ponzeveroni@gilbarco.com; roberto.celeste@gmail.com
License: UNKNOWN
Keywords: filesystem,parser,u-boot
Platform: UNKNOWN
Classifier: Programming Language :: Python
Classifier: Programming Language :: Python :: 3
Classifier: Development Status :: 4 - Beta
Classifier: Environment :: Other Environment
Classifier: Intended Audience :: Developers
Classifier: License :: OSI Approved :: GNU Library or Lesser General Public License (LGPL)
Classifier: Operating System :: OS Independent
Classifier: Topic :: Software Development :: Libraries :: Python Modules
